Workbook

Sheet Summary
A1: Process map: does each subject have every stage of its life?
A2: Subjects down the side, lifecycle stages across the top. A third cut: the Matrix asks whether an area has a dashboard, this asks whether a subject has a Failure process. Every cell is one of five things and they look different on purpose. A named process links to its row on the Processes sheet. An arrow means covered, by a process another area or another row owns. Trigger means covered, as a trigger on another row rather than a process of its own. n/a means deliberately not needed, with the reason. GAP means needed and nothing covers it. The Owner of a subject is accountable for every process in that row having an owner, and each process owner is accountable for everything in that process existing and working as intended. Owners here are suggestions. An amber owner is an escalation: the natural owner does not exist yet, so accountability sits higher until the role is filled, and is recorded that way so that it moves when the role is filled rather than staying put by default.
A4: Area | B4: Subject | C4: Owner | D4: Create / Change | E4: Exit | F4: Run | G4: Periodic Test / Review / Refresh | H4: Failure | I4: Fix | J4: Report
A5: People, fitness and accountability | B5: Roles | C5: CEO | D5: =Processes!$A$7 -> Creation of a role | E5: GAP: Abolishing or merging a role. Touches the accountability statement, the twin and the obligations that pointed at it. | F5: n/a: A role is a definition. It does not run. | G5: GAP: Re-examining a role: still needed, still correctly scoped, still a responsible-person or accountable-person role. | H5: n/a: A role cannot fail. The holder's fitness can, which is the row below. | I5: n/a: Nothing to remediate at the level of a definition. | J5: =Processes!$A$20 -> Regular reporting
B6: People | C6: CEO (escalated: would be Chief People Officer) | D6: =Processes!$A$9 -> Appointment of a person | E6: =Processes!$A$10 -> Departure and offboarding | F6: n/a: Covered by the role the person holds rather than by the person. | G6: =Processes!$A$11 -> Reassessing fitness and propriety | H6: -> Departure and offboarding. A fail outcome on reassessment routes there rather than being handled separately. | I6: n/a: A person who ceases to be fit is not remediated in place. | J6: =Processes!$A$20 -> Regular reporting
B7: Remuneration | C7: CEO (escalated: would be Chief People Officer) | D7: =Processes!$A$13 -> Remuneration review | E7: -> Departure and offboarding, which settles the deferral treatment. | F7: =Processes!$A$14 -> Remuneration payment | G7: Trigger: The annual cadence is the trigger on Remuneration review rather than a separate cycle. | H7: -> Incident, breach and issue. A substantiated breach opens the malus question, which runs inside Remuneration review. | I7: Trigger: Malus and clawback is a workflow inside Remuneration review. | J7: =Processes!$A$20 -> Regular reporting
B8: Training | C8: CEO (escalated: would be Chief People Officer) | D8: =Processes!$A$16&" and "&Processes!$A$17 -> Defining a training requirement and Authoring and maintaining training content | E8: GAP: Retiring a requirement when the obligation behind it goes, and what happens to the completion history that evidenced it. | F8: =Processes!$A$18 -> Issuing and tracking completion | G8: Trigger: The cadence per requirement and the content refresh are cron triggers on the rows above. | H8: Trigger: Non-completion escalation is a step inside the issuance workflow. | I8: n/a: Non-completion is chased rather than remediated. | J8: -> Regular reporting for the People area.
A9: Operational resilience | B9: Critical operation | C9: COO | D9: =Processes!$A$24 -> Defining or changing a critical operation | E9: GAP: An operation ceasing to be critical, and what happens to its tolerances, plans and test history. | F9: n/a: An operation runs continuously as the business. There is no process to start it. | G9: =Processes!$A$25&" and "&Processes!$A$28 -> Assessing capability against tolerances and Running a test | H9: =Processes!$A$30 -> Responding to a disruption | I9: =Processes!$A$26 -> Closing a resilience gap | J9: =Processes!$A$36 -> Regular reporting
B10: Provider | C10: COO | D10: =Processes!$A$32 -> Onboarding a material service provider | E10: =Processes!$A$34 -> Exiting a provider | F10: n/a: The provider delivers the service. There is nothing for the Company to run. | G10: =Processes!$A$33 -> Monitoring a provider | H10: -> Incident, breach and issue for the record, and to Responding to a disruption where a critical operation is engaged. A forced exit runs alongside. | I10: -> Closing a resilience gap, which is the same closure shape. | J10: =Processes!$A$36 -> Regular reporting
A11: Incident, breach and issue | B11: Issue | C11: CRO | D11: =Processes!$A$40&" and "&Processes!$A$41&" and "&Processes!$A$42 -> Reporting or detecting an issue and Triaging and classifying it and Investigating it | E11: n/a: An issue closes rather than exits, which is the Fix stage. | F11: n/a: An issue is an event, not something that runs. | G11: Trigger: The sixty-day investigation trigger is a cron trigger on Investigating it. | H11: n/a: The issue is itself the failure. Nothing sits behind it. | I11: =Processes!$A$44 -> Remediating and closing | J11: =Processes!$A$43&" and "&Processes!$A$46 -> Notifying a regulator and Regular reporting
A12: Compliance and obligations | B12: Instrument | C12: CRO | D12: =Processes!$A$50 -> Identifying a source instrument | E12: GAP: An instrument repealed, replaced, or ceasing to apply, and what happens to the obligations drafted from it. | F12: n/a: An instrument is a source, not an operation. | G12: Trigger: The annual sweep of the regulatory environment is a cron trigger on Identifying a source instrument. | H12: n/a: An instrument cannot fail. Failing to identify one is a compliance failure, recorded against the obligation. | I12: n/a: Nothing to remediate at the level of a source. | J12: -> Regular reporting for this area, which covers all three subjects.
B13: Obligation | C13: CRO | D13: =Processes!$A$51 -> Creating obligations from an instrument | E13: -> the instrument exit above, since obligations retire with the instrument that created them. | F13: n/a: An obligation is discharged by a control rather than run. | G13: =Processes!$A$52 -> Refreshing obligations when an instrument changes | H13: -> Recording a control failure, and to Incident, breach and issue where a regime engages. An obligation fails through the control that discharges it. | I13: -> Remediating and closing in the incident area, which is the same closure shape. | J13: -> Regular reporting for this area.
B14: Control | C14: CRO, with a first-line owner per domain | D14: =Processes!$A$54&" and "&Processes!$A$55 -> Defining or changing a control and Linking a control to an obligation | E14: GAP: Retiring a control, and confirming what discharges the obligations it was carrying before it goes. | F14: Trigger: A control operates at its own frequency, held on the control record rather than as a process here. | G14: =Processes!$A$56 -> Testing a control | H14: =Processes!$A$57 -> Recording a control failure | I14: -> Remediating and closing in the incident area. | J14: =Processes!$A$59 -> Regular reporting
A15: Information security | B15: Information asset | C15: COO | D15: =Processes!$A$63 -> Classifying an information asset | E15: GAP: Decommissioning an asset: data destruction or return, access revocation, and removal from the inventory. A classic control failure point and nothing covers it. | F15: n/a: The asset is operated by the systems that use it. | G15: Trigger: Reclassification review is a cron trigger on Classifying an information asset. | H15: -> Responding to a security incident, and to the incident store for the record. | I15: -> Remediating and closing in the incident area. | J15: =Processes!$A$71 -> Regular reporting
B16: Access | C16: COO | D16: =Processes!$A$64 -> Granting, changing or revoking access | E16: Trigger: Revocation is the third transition on the row above rather than a process of its own, and it is fired by Departure and offboarding. | F16: n/a: Access is a state, not an operation. | G16: =Processes!$A$65 -> Recertifying access | H16: -> Responding to a security incident. Unauthorised access is a security event. | I16: -> Remediating and closing in the incident area. | J16: =Processes!$A$71 -> Regular reporting
B17: Security incident | C17: COO, with the record owned by the CRO | D17: -> Reporting or detecting an issue. Capture is the incident area's, through the four-button entry page. | E17: n/a: An incident closes rather than exits. | F17: n/a: An incident is an event. | G17: =Processes!$A$67 -> Running a security test | H17: n/a: The incident is itself the failure. | I17: =Processes!$A$69 -> Responding to a security incident | J17: =Processes!$A$71 -> Regular reporting
A18: Data governance | B18: Data item | C18: COO, with an accountable executive per domain | D18: =Processes!$A$75 -> Defining or changing a data item | E18: GAP: Retiring a data item, and what happens to the rules, reports and decisions that referenced it. | F18: n/a: A definition does not run. | G18: Trigger: The periodic review of definitions against what the systems hold is a cron trigger on Defining or changing a data item. | H18: =Processes!$A$78 -> Running the rules and raising issues | I18: =Processes!$A$79 -> Resolving a data quality issue | J18: =Processes!$A$86 -> Regular reporting
B19: Data quality rule | C19: COO | D19: =Processes!$A$77 -> Defining a data quality rule | E19: GAP: Retiring a rule, and whether the domain is left with no test of that kind. | F19: =Processes!$A$78 -> Running the rules and raising issues | G19: GAP: Reviewing whether the thresholds are still right. A threshold nobody revisits either never fires or always fires. | H19: n/a: A rule does not fail. It detects failure, which is the Failure stage on the row above. | I19: -> Resolving a data quality issue. | J19: =Processes!$A$86 -> Regular reporting
B20: End-user computing tool | C20: COO | D20: =Processes!$A$81 -> Registering an end-user computing tool | E20: GAP: Retiring a tool, which is the good outcome when the platform takes over its job, and worth recording as evidence that the inventory is shrinking rather than growing. | F20: n/a: The tool is run by its owner outside the platform, which is the point of inventorying it. | G20: =Processes!$A$82 -> Reconciling an end-user computing tool | H20: -> Running the rules and raising issues where the tool feeds a tested item; otherwise to the incident area. | I20: -> Resolving a data quality issue. | J20: =Processes!$A$86 -> Regular reporting
B21: De-identification method | C21: CRO | D21: =Processes!$A$84 -> Confirming a de-identification method before use | E21: n/a: A method is superseded by confirming a different one for the use. | F21: Trigger: The method is applied by the process that uses the data, not run from here. | G21: GAP: Re-confirming a method still fit for a use it was approved for. Re-identification risk rises as other data becomes available, so a confirmation does not stay true. | H21: -> Responding to a security incident, and to Privacy for a notifiable data breach. | I21: -> Remediating and closing in the incident area. | J21: =Processes!$A$86 -> Regular reporting
A22: Conflicts and related party | B22: Conflict | C22: CRO, or the Chair where a director is involved | D22: =Processes!$A$90 -> Disclosing a conflict and deciding the response | E22: Trigger: Cessation is an outcome on Reviewing a conflict rather than a process of its own. | F22: n/a: A conflict is a state that is managed, not an operation that runs. | G22: =Processes!$A$91 -> Reviewing a conflict | H22: -> Incident, breach and issue, where a conflict was not disclosed or the agreed response was not followed. | I22: -> Remediating and closing in the incident area. | J22: =Processes!$A$97 -> Regular reporting
B23: Related-party arrangement | C23: Company Secretary, approved by the unaffiliated directors | D23: =Processes!$A$93 -> Approving a related-party arrangement | E23: =Processes!$A$95 -> Ending or renegotiating an arrangement | F23: n/a: The arrangement operates as the commercial relationship. There is nothing to run from here. | G23: =Processes!$A$94 -> Reviewing a related-party arrangement | H23: -> Incident, breach and issue, where an arrangement operated outside its approved terms. | I23: -> Remediating and closing in the incident area. | J23: =Processes!$A$97 -> Regular reporting
A24: Risk management | B24: Risk | C24: CRO | D24: =Processes!$A$101&" and "&Processes!$A$102 -> Identifying a risk and Assessing and rating a risk | E24: Trigger: Closure with a reason is an outcome on Reviewing a risk. | F24: n/a: A risk is a state that is managed, not an operation. | G24: =Processes!$A$103 -> Reviewing a risk | H24: -> Incident, breach and issue. A risk materialising is an event, recorded there. | I24: =Processes!$A$104 -> Treating a risk | J24: =Processes!$A$106 -> Regular reporting
A25: Delegations and Board | B25: Delegation | C25: Company Secretary | D25: =Processes!$A$110 -> Setting or changing a delegation | E25: GAP: Revoking a delegation, and confirming nothing still relies on it. | F25: =Processes!$A$111 -> Exercising an authority | G25: Trigger: The periodic review of limits is a cron trigger on the create row. | H25: -> Incident, breach and issue, where an authority was exercised outside its limit. | I25: -> Remediating and closing in the incident area. | J25: =Processes!$A$116 -> Regular reporting
B26: Board and committee cycle | C26: Company Secretary | D26: GAP: Establishing or changing a committee: its charter, membership and standing items. | E26: n/a: A committee is dissolved by the Board rather than through a process of its own. | F26: =Processes!$A$113 -> Running a Board or committee cycle | G26: =Processes!$A$114 -> Assessing the Board and its committees | H26: n/a: A cycle that does not run is visible on the dashboard rather than raised as a failure. | I26: n/a: Nothing to remediate. | J26: =Processes!$A$116 -> Regular reporting
A27: Internal audit | B27: Audit engagement | C27: Head of Internal Audit (outsourced: escalates to the Audit Committee Chair) | D27: =Processes!$A$120 -> Planning the audit cycle | E27: n/a: An engagement completes rather than exits. | F27: =Processes!$A$121 -> Running an engagement | G27: Trigger: The annual plan and the three-year rolling coverage are cron triggers on the planning row. | H27: n/a: An engagement that does not run shows as coverage missed on the dashboard. | I27: =Processes!$A$123 -> Closing a finding | J27: =Processes!$A$125 -> Regular reporting
A28: AI governance | B28: AI use case | C28: CTO, with the CRO for the determination | D28: =Processes!$A$129&" and "&Processes!$A$130 -> Registering an AI use case and Changing or revalidating a model | E28: GAP: Retiring a model or use case, and what happens to the decisions it made and the disclosures that referenced it. | F28: =Processes!$A$132 -> Monitoring AI decisioning | G28: Trigger: Periodic revalidation is a cron trigger on the change row. | H28: -> Responding to a security incident for an AI system operating outside its function, and to Incident, breach and issue for a wrong decision. | I28: -> Remediating and closing in the incident area. | J28: =Processes!$A$134 -> Regular reporting
A29: Privacy | B29: Personal information holding | C29: CRO | D29: =Processes!$A$138 -> Recording what personal information is held | E29: =Processes!$A$144 -> Retaining and destroying | F29: n/a: A holding is a state rather than an operation. | G29: Trigger: The periodic confirmation against what systems hold is a cron trigger on the create row. | H29: -> Incident, breach and issue, and the notifiable data breach path. | I29: -> Remediating and closing in the incident area. | J29: =Processes!$A$146 -> Regular reporting
B30: Privacy impact assessment | C30: CRO | D30: =Processes!$A$140 -> Assessing a privacy impact | E30: n/a: An assessment completes rather than exits. | F30: n/a: An assessment is an event. | G30: GAP: Re-assessing where a project changed after its assessment. An assessment describes a design, and designs move. | H30: n/a: The finding is the failure, and it goes to closure. | I30: -> Remediating and closing in the incident area. | J30: =Processes!$A$146 -> Regular reporting
B31: Data subject request | C31: CRO | D31: =Processes!$A$142 -> Handling a data subject request | E31: n/a: A request is answered rather than exited. | F31: n/a: A request is an event. | G31: n/a: Nothing recurs per request. | H31: -> Incident, breach and issue, where a statutory deadline is missed. | I31: -> Remediating and closing in the incident area. | J31: =Processes!$A$146 -> Regular reporting
A32: Financial crime | B32: Screening | C32: CUO | D32: Trigger: Screening is a step inside onboarding and claims rather than a process started here. | E32: n/a: A screening record is retained rather than exited. | F32: =Processes!$A$150 -> Screening a customer, adviser or counterparty | G32: =Processes!$A$152 -> Keeping the lists current | H32: =Processes!$A$151 -> Reviewing an alert | I32: -> Remediating and closing in the incident area, where an alert engages a reporting obligation. | J32: =Processes!$A$156 -> Regular reporting
B33: AML/CTF regime applicability | C33: CRO | D33: =Processes!$A$154 -> Maintaining the applicability analysis | E33: n/a: The analysis is superseded rather than retired. | F33: n/a: An analysis is a conclusion, not an operation. | G33: Trigger: The annual review and the roadmap-change trigger sit on the row above. | H33: GAP: What happens when the conclusion flips: the program that has to exist before an investment-linked or annuity product launches, and how long that takes. | I33: n/a: Nothing to remediate. | J33: =Processes!$A$156 -> Regular reporting
A34: Product and pricing | B34: Product | C34: CUO | D34: =Processes!$A$160 -> Defining or changing a product | E34: =Processes!$A$161 -> Retiring a product | F34: n/a: A product is administered through the policy lifecycle in core business operations. | G34: Trigger: The periodic pricing review is a cron trigger on Repricing. | H34: -> Incident, breach and issue, where a product operated outside its terms or a disclosure was wrong. | I34: -> Remediating and closing, and customer remediation where policyholders were affected. | J34: =Processes!$A$165 -> Regular reporting
B35: Rating basis | C35: CUO, on the Appointed Actuary's advice | D35: =Processes!$A$163 -> Repricing | E35: Trigger: A rating table is superseded by an effective-dated replacement rather than retired. | F35: n/a: Rates are applied by the pricing calculator inside underwriting. | G35: -> Experience analysis in Actuarial and capital, which is what tells you the rates no longer hold. | H35: GAP: Rates found to be wrong after policies were written on them: identifying the affected cohort and deciding whether to reprice, remediate or absorb. | I35: -> Customer remediation in the incident area. | J35: =Processes!$A$165 -> Regular reporting
A36: Distribution and adviser | B36: Adviser | C36: CUO | D36: =Processes!$A$169 -> Onboarding an adviser or dealer group | E36: =Processes!$A$170 -> Offboarding an adviser | F36: n/a: The adviser writes business through the portal; there is nothing to run from here. | G36: Trigger: Authorisation re-verification is a cron trigger on the onboarding row. | H36: -> Incident, breach and issue, where an adviser wrote business without a current authorisation or advised unsuitably. | I36: -> Remediating and closing, and customer remediation where policyholders were affected. | J36: =Processes!$A$177 -> Regular reporting
B37: Commission | C37: CFO | D37: Trigger: The scale is set at adviser onboarding and at product definition. | E37: n/a: A commission arrangement ends with the adviser. | F37: =Processes!$A$175 -> Paying commission | G37: GAP: Confirming paid commission matches the scale and the policy. A commission run nobody reconciles is a leakage nobody sees. | H37: -> Incident, breach and issue for an overpayment or a LIF breach. | I37: -> Remediating and closing. | J37: =Processes!$A$177 -> Regular reporting
A38: Actuarial and capital | B38: Assumption set | C38: Appointed Actuary (vacant: escalates to the CFO) | D38: =Processes!$A$181 -> Setting and changing assumptions | E38: Trigger: An assumption is superseded by a versioned replacement rather than retired. | F38: -> Running a valuation, which is what consumes the assumption set. | G38: =Processes!$A$184 -> Analysing experience | H38: GAP: An assumption found wrong after a valuation was signed on it: restating, and what that means for a return already lodged. | I38: -> Remediating and closing in the incident area. | J38: =Processes!$A$189 -> Regular reporting
B39: Capital position | C39: CFO | D39: -> the business plan and the ICAAP set the target; this is not created per period. | E39: n/a: A capital position does not retire. | F39: =Processes!$A$186 -> Monitoring capital adequacy | G39: =Processes!$A$187 -> Running the ICAAP cycle | H39: -> the Recovery and Exit Plan at ACT-2, and to Incident, breach and issue for the prudential notification. | I39: -> the recovery actions in ACT-2, tracked through the closure shape. | J39: =Processes!$A$189 -> Regular reporting
A40: Reinsurance | B40: Treaty | C40: CFO, negotiated by the CEO per the FAR exclusions | D40: =Processes!$A$193 -> Placing a treaty | E40: =Processes!$A$194 -> Ending or replacing a treaty | F40: =Processes!$A$196 -> Ceding and recovering | G40: Trigger: Renewal is a trigger on the placing row. | H40: -> Incident, breach and issue, where a cession was not made or a treaty lapsed uncovered. | I40: -> Remediating and closing. | J40: =Processes!$A$200 -> Regular reporting
B41: Counterparty | C41: CFO | D41: Trigger: A counterparty arrives with a treaty and is also onboarded as a material service provider. | E41: -> Exiting a provider in operational resilience, and Ending or replacing a treaty here. | F41: =Processes!$A$198 -> Monitoring the counterparty | G41: -> Monitoring a provider in operational resilience. | H41: GAP: A reinsurer failing or disputing: what the Company does about recoveries in flight and a book priced on cover it may not have. | I41: -> the Recovery and Exit Plan at ACT-2. | J41: =Processes!$A$200 -> Regular reporting
A42: Finance operations | B42: Receipt | C42: CFO | D42: =Processes!$A$204 -> Receiving and allocating money | E42: Trigger: A receipt is allocated or refunded rather than retired. | F42: =Processes!$A$204 -> Receiving and allocating money | G42: -> Reconciling, which is what confirms allocation was right. | H42: -> the failed payment workflow in core business operations, and to Incident, breach and issue where money is misallocated. | I42: -> Remediating and closing. | J42: =Processes!$A$213 -> Regular reporting
B43: Payment | C43: CFO | D43: =Processes!$A$206 -> Paying money out | E43: n/a: A payment completes or is reversed. | F43: =Processes!$A$206 -> Paying money out | G43: -> Reconciling. | H43: -> Incident, breach and issue, where a payment was made outside a limit or in error. | I43: -> Remediating and closing. | J43: =Processes!$A$213 -> Regular reporting
B44: Accounting period | C44: CFO | D44: n/a: A period opens on a calendar rather than being created. | E44: =Processes!$A$209 -> Closing a period | F44: =Processes!$A$208 -> Reconciling | G44: Trigger: The audit of the annual statements is a trigger on the close row. | H44: GAP: Reopening a closed period, and what that means for a return already lodged on it. | I44: -> Remediating and closing. | J44: =Processes!$A$213 -> Regular reporting
B45: Tax obligation | C45: CFO | D45: Trigger: An obligation arrives with a product, a state, or an employment arrangement rather than being created here. | E45: n/a: A tax obligation ends when the activity behind it does. | F45: =Processes!$A$211 -> Meeting tax obligations | G45: GAP: Confirming the obligation set is complete: which states, which duties, which thresholds. Nobody has listed them. | H45: -> Incident, breach and issue for a late or wrong lodgement. | I45: -> Remediating and closing. | J45: =Processes!$A$213 -> Regular reporting
A46: Investment management | B46: Mandate | C46: CFO | D46: =Processes!$A$217 -> Setting and changing the mandate | E46: n/a: A mandate is replaced rather than retired. | F46: =Processes!$A$219 -> Running the portfolio | G46: =Processes!$A$217 -> Setting and changing the mandate | H46: -> incident, where a limit breach is material or repeated. | I46: -> Remediating and closing. | J46: =Processes!$A$225 -> Regular reporting
B47: Portfolio | C47: CFO | D47: Trigger: Holdings change on a trade or a cash movement rather than being created. | E47: n/a: The portfolio persists; individual holdings are sold. | F47: =Processes!$A$219 -> Running the portfolio | G47: =Processes!$A$223 -> Holding the assets | H47: =Processes!$A$219 -> Running the portfolio | I47: -> Remediating and closing. | J47: =Processes!$A$225 -> Regular reporting
B48: External manager | C48: CFO | D48: =Processes!$A$221 -> Overseeing the manager | E48: -> the provider exit path in Operational resilience, which is where the exit plan lives. | F48: =Processes!$A$221 -> Overseeing the manager | G48: =Processes!$A$221 -> Overseeing the manager | H48: -> incident, and to the provider gap path in Operational resilience. | I48: -> Remediating and closing. | J48: =Processes!$A$225 -> Regular reporting
B49: Statutory fund attribution | C49: CFO | D49: Trigger: An asset is attributed when it is acquired. | E49: Trigger: Attribution ends when the asset leaves the fund. | F49: =Processes!$A$223 -> Holding the assets | G49: =Processes!$A$223 -> Holding the assets | H49: -> incident: an unattributed or misattributed asset is a Life Act s38 matter. | I49: -> Remediating and closing. | J49: =Processes!$A$225 -> Regular reporting
A50: Regulatory and financial reporting | B50: Reporting obligation | C50: CFO | D50: =Processes!$A$229 -> Recording an obligation | E50: Trigger: An obligation ends when the regime or the activity behind it does. | F50: =Processes!$A$231 -> Preparing and lodging a return | G50: =Processes!$A$229 -> Recording an obligation | H50: -> incident: a missed or late lodgement is a breach. | I50: =Processes!$A$232 -> Correcting a lodged return | J50: =Processes!$A$234 -> Regular reporting
B51: Return | C51: CFO | D51: =Processes!$A$231 -> Preparing and lodging a return | E51: n/a: A return is lodged and closed rather than retired. | F51: =Processes!$A$231 -> Preparing and lodging a return | G51: Trigger: The audit and the actuarial review are triggers on the preparation row. | H51: =Processes!$A$232 -> Correcting a lodged return | I51: =Processes!$A$232 -> Correcting a lodged return | J51: =Processes!$A$234 -> Regular reporting
A52: Core business operations | B52: Policy | C52: COO | D52: =Processes!$A$238 -> Selling and issuing a policy | E52: =Processes!$A$241 -> Collecting premium and losing a policy | F52: =Processes!$A$240 -> Servicing and altering a policy | G52: Trigger: Renewal and anniversary are triggers on the servicing row. | H52: -> incident, where a policy was issued or altered wrongly. | I52: -> Remediating and closing, and to customer remediation where a cohort is affected. | J52: =Processes!$A$251 -> Regular reporting
B53: Claim | C53: COO | D53: =Processes!$A$243 -> Paying a claim | E53: Trigger: A claim closes on payment or decline. | F53: =Processes!$A$243 -> Paying a claim | G53: GAP: Post-decision quality review of a sample of claim decisions, including AI-made ones. Nothing asserts one. | H53: -> incident, and to Complaints where the customer disputes it. | I53: -> Remediating and closing. | J53: =Processes!$A$251 -> Regular reporting
B54: Complaint | C54: COO | D54: =Processes!$A$245 -> Handling a complaint | E54: Trigger: A complaint closes on response or on AFCA determination. | F54: =Processes!$A$245 -> Handling a complaint | G54: =Processes!$A$251 -> Regular reporting | H54: -> incident, where the RG 271 timeframe is missed. | I54: -> the issue path, where a complaint pattern is systemic. | J54: =Processes!$A$251 -> Regular reporting
B55: Customer request | C55: COO | D55: =Processes!$A$249 -> Responding to a data subject request | E55: Trigger: A request closes on response. | F55: =Processes!$A$249 -> Responding to a data subject request | G55: -> Data governance, where catalogue accuracy is what makes a response possible. | H55: -> Privacy, and to incident where the timeframe is missed. | I55: -> Remediating and closing. | J55: =Processes!$A$251 -> Regular reporting
A56: Infrastructure and platform | B56: Environment or service | C56: CTO | D56: =Processes!$A$255 -> Standing up or retiring an environment or service | E56: =Processes!$A$255 -> Standing up or retiring an environment or service | F56: =Processes!$A$259 -> Running and monitoring the platform | G56: =Processes!$A$260 -> Testing recovery | H56: -> incident, and to Operational resilience where a critical operation is affected. | I56: -> Remediating and closing. | J56: =Processes!$A$264 -> Regular reporting
B57: Change | C57: CTO | D57: =Processes!$A$257 -> Changing the platform | E57: Trigger: A change is released, reversed or abandoned. | F57: =Processes!$A$257 -> Changing the platform | G57: Trigger: The emergency change review window is a trigger on the change row. | H57: -> incident: a failed change is the most common cause of an availability incident. | I57: -> Remediating and closing. | J57: =Processes!$A$264 -> Regular reporting
B58: Function | C58: CTO | D58: =Processes!$A$262 -> Keeping the function inventory current | E58: n/a: A function is superseded in the inventory rather than retired as a subject. | F58: Trigger: A function runs when a workflow task calls it. | G58: GAP: Confirming the inventory against the codebase. Nothing asserts one, and without it the inventory decays into an estimate again. | H58: -> incident, where a function fails in a workflow. | I58: -> Changing the platform. | J58: =Processes!$A$264 -> Regular reporting
B59: Access | C59: CTO | D59: -> Information security, where access provisioning and review live. | E59: -> Information security, and to People for the departure trigger. | F59: -> Information security. | G59: -> Information security, where the access review cycle sits. | H59: -> incident. | I59: -> Remediating and closing. | J59: -> Information security reporting.
A60: Document suite | B60: Document | C60: CRO | D60: =Processes!$A$268 -> Creating or revising a document | E60: =Processes!$A$269 -> Retiring or superseding a document | F60: Trigger: A document is read and cited rather than run. | G60: =Processes!$A$268 -> Creating or revising a document | H60: GAP: An out-of-date approved document being relied on. Nothing detects it beyond the review clock. | I60: =Processes!$A$268 -> Creating or revising a document | J60: =Processes!$A$271 -> Confirming the suite covers the standards
B61: Coverage of a standard | C61: CRO | D61: =Processes!$A$271 -> Confirming the suite covers the standards | E61: Trigger: Coverage ends when the standard is withdrawn. | F61: Trigger: Coverage is asserted at approval and confirmed on the cycle. | G61: =Processes!$A$271 -> Confirming the suite covers the standards | H61: -> Compliance and obligations, where an undischarged obligation is the same finding. | I61: =Processes!$A$268 -> Creating or revising a document | J61: =Processes!$A$271 -> Confirming the suite covers the standards
A62: Programme activities | B62: Programme activity | C62: CEO | D62: =Processes!$A$275 -> Running a programme activity to completion | E62: Trigger: An activity closes when its evidence is held. | F62: =Processes!$A$275 -> Running a programme activity to completion | G62: n/a: The activity is itself the test; it is not separately reviewed. | H62: Trigger: An activity that misses its objective raises a gap on the same row. | I62: -> Remediating and closing, which is where every gap converges. | J62: =Processes!$A$277 -> Reaching a gate
B63: Gate | C63: CEO | D63: n/a: The two gates are fixed by the application, not created. | E63: =Processes!$A$277 -> Reaching a gate | F63: =Processes!$A$277 -> Reaching a gate | G63: =Processes!$A$277 -> Reaching a gate | H63: GAP: What happens if a gate is missed: no replan process is defined, and the go-live gate is conditional rather than dated. | I63: -> Remediating and closing. | J63: =Processes!$A$277 -> Reaching a gate
A65: 59 subjects x 7 stages = 413 cells: 185 covered by a process of their own, 98 covered elsewhere, 46 covered by a trigger, 57 deliberately not needed, and 27 gaps.

Sheet Processes
A1: By process: what one real-world event needs
A2: One row per real-world event, grouped by the thing the event acts on. A blue cell means the system has to provide that thing for this process, whether or not any of it is built: this sheet states what is required, not what is done. Grey means deliberately not required, and the cell says why. The blue block runs left to right from what fires the process to what comes out of it. Trigger is blue because a trigger is configuration the system has to hold: a cron schedule, or a watched location or form submission. Where a tool is required the cell carries the count, and where the count hides variation it carries the axis of variation too, because both deep dives found that 'one' was the wrong answer. These rows are a view, not register entries; the items behind them carry BR numbers on the deep dive sheets.
A4: Process | B4: Summary | C4: Register (stores written) | D4: Trigger | E4: Entry form | F4: Workflow | G4: Dashboard | H4: Document | I4: Report / return | J4: Notes
A5: People, fitness and accountability | B5: Substitutability, twinning and cross-skilling, is carried here rather than under operational resilience: the data sits on the role record, and the events that change it are appointment and departure. The resilience dashboards read it.
A6: The role
A7: Creation of a role | B7: Defines the thing everything else hangs off, including whether it is a responsible-person or accountable-person role. | C7: People (role), Required competencies, Delegated authorities | D7: Input: the CEO or the Board proposes a role, or an existing role is materially changed. | E7: 1: role definition, carrying the responsible-person and accountable-person flags and the competencies the role requires. | F7: 1, with 2 approval paths: the Board for an accountable-person role, the CEO otherwise. | G7: a slice of the accountability and fitness dashboard: roles filled and vacant, and which are responsible-person or accountable-person roles. | H7: Role description | I7: n/a | J7: Whether the role is a CPS 520 responsible-person role, a FAR accountable-person role, both or neither is decided here. That decision drives the four paths in the appointment process below, so getting it wrong at role creation propagates. No return files at this point: notification happens on appointment, not on creation.
A8: The person
A9: Appointment of a person | B9: The keystone: one event writes five stores, on four paths depending on what kind of role it is. | C9: People, Fit and proper, Competency, Access, Remuneration ledger | D9: Input: an accepted offer. Blocked until the fit and proper initial assessment completes. | E9: 3: appointment and role change; fit and proper declaration with standing consent; competency evidence. | F9: 1, with 4 paths: responsible person / accountable person / both / neither. Calls 2 sub-workflows: fit and proper initial assessment, and accountability statement drafting and approval. | G9: 1: accountability and fitness, showing status per person and anything overdue. | H9: Employment contract; accountability statement (accountable persons only) | I9: CPS 520 responsible person notification; FAR accountability map lodgement | J9: This is the line for the appointment of a person. Fit and proper must complete before appointment for a responsible person, an accountability statement must be drafted and Board approved for an accountable person, both apply where the role is both, and neither applies for an ordinary hire. Every store listed is written by this one event, which is why it is the keystone of the area.
A10: Departure and offboarding | B10: One event that should touch five stores. Today the five obligations exist and the join does not. | C10: People, Access, Twinning, System operators, Remuneration ledger | D10: Input: a resignation or a dismissal. Also cron, on a fixed-term end date. | E10: 1: departure notice with the reason, since the reason is what raises the s32 and malus questions. | F10: 1, with 5 branches, one per store touched: revoke access, settle the deferral treatment, invalidate twinning, invalidate system-operator entries, lodge the cessation notification. | G10: a slice of the accountability and fitness dashboard: open offboarding actions and anything outstanding. | H10: Termination letter; reissued accountability statement for any role reassigned | I10: CPS 520 cessation notification; FAR s32 notification where the departure is a dismissal | J10: One event touching five stores. Those five obligations exist separately in the document set and nothing joins them, which is the gap this row exists to make visible.
A11: Reassessing fitness and propriety | B11: Annual, plus on a trigger event. Only the initial assessment was written into Appointment; the recurring cycle had no process row. | C11: Fit and proper assessment records | D11: Cron, annual, fanned out per responsible person. Also input, on a trigger event: a criminal charge, a bankruptcy, a disqualification, or a substantiated breach. | E11: 1: refreshed declaration and confirmation that the standing consent still holds. | F11: 1: the assessment shape. Propriety checks refreshed as system tasks where a source supports it, fitness assessed against the role's required competencies, and a fail outcome routed to the departure process. | G11: 1: a slice of the accountability and fitness dashboard, showing reassessments due and overdue. | H11: n/a: the assessment is a record rather than a document. | I11: Where a person ceases to be fit, the cessation notification and any FAR s32 notification file through the departure process rather than from here. | J11: Found by the Map: the initial assessment sits inside Appointment and the recurring cycle existed only as a register workflow with no process row of its own. The fail outcome is the interesting path, because it has to reach Departure and nothing joined them.
A12: Remuneration
A13: Remuneration review | B13: Annual, but opened out of cycle by a substantiated breach, which is how malus reaches an award. | C13: Remuneration ledger, People (material risk-taker attribute) | D13: Cron, annual. Also input, on a substantiated breach or an s32 event, which is what opens the malus question out of cycle. | E13: 2: performance and risk input per person; the Board's remuneration decision. | F13: 2: the annual review cycle, and malus or clawback determination on a triggering event. | G13: 1: deferral positions and vesting, the material risk-taker population, and any adjustment applied. | H13: Individual remuneration outcome letters | I13: Remuneration disclosure [confirm whether a CPS 511 return applies at this scale] | J13: Reads the incident store as well as the ledger: GOV-4 makes a substantiated breach a relevant consideration in a remuneration outcome and PPL-5 §5 sets the criteria, so malus sits inside this process rather than beside it. The material risk-taker population is refreshed here as a criteria-driven attribute rather than maintained as a list.
A14: Remuneration payment | B14: A read of the ledger rather than a decision: the schedule was set at review. | C14: Remuneration ledger (vesting and payment status), Bank payment records, General ledger | D14: Cron, from the vesting schedule and the payroll calendar. | E14: n/a: the award and its schedule were captured at review, and a payment run reads them. | F14: 1, with dual authorisation. | G14: a slice of the remuneration dashboard: payments due, deferrals vesting, and exceptions. | H14: Payslip and remittance | I14: PAYG, single touch payroll and payroll tax [outside the APRA set] | J14: Deferred amounts vest from the ledger rather than being decided again, which is the point of holding the schedule as data. The absent entry form is the design working, not a gap.
A15: Training
A16: Defining a training requirement | B16: One register of requirements rather than a training row per policy. | C16: Training requirements register | D16: Input: a document creates or changes a training or awareness obligation. Also cron, a periodic sweep of the suite for obligations nobody has listed. | E16: 1: requirement definition, with the population it applies to, the cadence, and the document that requires it. | F16: 1: the CEO defines the requirement, AI drafts which documents in the suite create a training obligation and whether any is unmet, the CEO confirms, and issuance is scheduled. | G16: 1: a slice of the accountability and fitness dashboard, showing requirements and their populations. | H16: n/a: the requirement is data. The content it issues is the row below. | I16: n/a | J16: At least four documents name a training or awareness obligation: GOV-4 the code of conduct, GOV-9 conflicts, GOV-10 whistleblower awareness, and PPL-5 risk culture. Several others probably do, and none is confirmed, which is why the AI step drafts the list rather than assuming someone has it. QUESTION for the design phase: whether security awareness under CPS 234, privacy under CUS-6 and AML/CTF training under CPL-1 are in scope.
A17: Authoring and maintaining training content | B17: The item that had nobody accountable for it, which is why the ownership escalation is recorded rather than assumed. | C17: Training content, versioned | D17: Input: a new requirement, or a material change to the policy the content teaches. Also cron, a periodic refresh. | E17: 1: content and the requirement it satisfies. | F17: 1: the publish shape. AI drafts or refreshes against the requirement and the current policy, the content owner reviews, an approver publishes, and the version supersedes the prior one. | G17: n/a: content currency shows on the completion view rather than needing its own. | H17: The content itself, per requirement. | I17: n/a | J17: Versioning is what makes a completion record mean anything: it records which version a person completed, so a material policy change can invalidate completions rather than leaving everyone marked trained on superseded content. Reissue triggers on a policy change, not only on the cadence.
A18: Issuing and tracking completion | B18: Attestation shape, fanned out per person per requirement. | C18: Training completion records | D18: Cron, at induction and at each requirement's cadence, fanned out per person per requirement. Also input, on a new starter or a content version that invalidates prior completions. | E18: 1: completion and attestation by the person. | F18: 1: issue, the person completes and attests, completion is recorded against the content version, and non-completion escalates. | G18: 1: a slice of the accountability and fitness dashboard, showing completion by requirement and anything overdue. | H18: n/a | I18: n/a | J18: Fires from Appointment for a new starter, which is the coupling that matters: a person who joins and is never issued their induction training is a completion record that never existed rather than one that is overdue, and only the requirement register makes that visible.
A19: Reporting
A20: Regular reporting | B20: One calendar for the Board and committee cycle, the APRA returns and the annual confirmations. | C20: Lodgement and submission records, Board pack | D20: Cron, from the reporting calendar: Board and committee meeting dates, APRA return due dates, and the annual submission dates. | E20: 1: management commentary and exception explanation. The numbers are system-generated; the narrative is not. | F20: 3, one per cadence: the Board and committee cycle, APRA return preparation and reconciliation, and the annual submissions. | G20: 1: reporting readiness and what is overdue, which is what makes the claim that month-end reconciliation is automatic testable. | H20: Board and committee papers; minutes | I20: APRA returns; annual MSP register submission; annual FAR and CPS 520 confirmations | J20: One calendar rather than three. The three cadences differ in due date and approver but not in shape, so they are three configurations rather than three builds.
A22: Operational resilience | B22: A change that invalidates a capability state, infrastructure delivered or withdrawn or a provider changing what it will commit to, is a second trigger on the capability assessment rather than a process of its own.
A23: The critical operation
A24: Defining or changing a critical operation | B24: The analogue of role creation. The Board approves the operation and its three tolerances, versioned so a later incident is judged against the tolerance then in force. | C24: Critical operations, with its versioned tolerance sets | D24: Input: the COO proposes a new critical operation or an amended tolerance set. Also input, on a business change that adds or removes an operation. | E24: 1: operation and tolerance proposal, carrying all three tolerance dimensions. | F24: 1, with a Board approval gate. Versions the tolerance set with its approval reference and effective date. | G24: 1: critical operations and capability, showing the operative tolerance per operation and dimension. | H24: n/a: OPS-2 is the framework and sits in the suite. An operation is data, not a document. | I24: n/a: nothing files on definition. The register reaches APRA through the annual Board paper at the last row. | J24: Point-in-time versioning is what makes this more than a list: an incident months later has to be judged against the tolerance in force at the time, not today's. The register exists and is built; the proposal form and the approval workflow do not, so the eight operations were loaded once and there is no governed way to change them.
A25: Assessing capability against tolerances | B25: Annual, fanned out eight operations by three dimensions, and reopened by any change that bears on a tolerance. | C25: Capability assessment records (children of critical operations), Cross-cutting gaps | D25: Cron, annual, fanned out eight operations by three dimensions. Also input, on a change that bears on a tolerance: infrastructure delivered or withdrawn, or a provider changing what it will commit to. That reopens the affected dimension rather than waiting for the cycle. | E25: n/a: the assessor's judgement and its evidence are the workflow's human task, not a separate form. | F25: 2: the annual cycle, and re-assessment on a trigger. Both write a five-state outcome per dimension and raise anything short into the gap process below. | G25: 1: critical operations and capability, showing capability state against the operative tolerance. | H25: n/a | I25: n/a: feeds the annual Board paper at the last row. | J25: Much of this is derivable, since a tolerance, a tested recovery time and an infrastructure recovery objective are all data. The five-state field exists for the dimensions not yet tested, and it is that judgement and its evidence that need storing. The fan-out this needs, eight by three, is recorded as untested rather than known to fail, and it is now on the critical path for a licence-gated item.
A26: Closing a resilience gap | B26: Raised by the assessment, by a test result, or by anyone who notices one, and tracked to closure. | C26: Cross-cutting gaps | D26: Input: a gap raised by the capability assessment, by a test result, or out of cycle by anyone who notices one. | E26: 1: out-of-cycle gap notification. The assessment and test paths raise gaps without a form. | F26: 1: the closure shape. Owner, target date, progress, closure evidence, acceptance or reopen, with overdue escalation. | G26: 1: a slice of the critical operations and capability dashboard, showing open gaps by age and by operation. | H26: n/a | I26: n/a | J26: The register has a status field and nothing drives it. Identical in shape to audit findings, privacy impact assessment findings and controls assurance remediation, so it is one workflow configured four ways rather than four workflows.
A27: Testing
A28: Running a test | B28: One process, three configurations, all writing to the shared execution store. Security control testing is the fourth, over in information security. | C28: Test execution store, Test scenario library | D28: Cron, from the scenario schedule. Also input, where a test is called early after a change or a near-miss. | E28: 2: scenario proposal into the library; test result capture, including a partial or failed result. | F28: 3 configurations of one shape: resilience scenario test, business continuity and crisis test, provider exit plan test. A fourth, security control and penetration testing, is the same shape in information security. | G28: 1: resilience testing, showing what has been tested, the results, and which capability states remain unresolved for want of a test. | H28: The BCP action plan and the crisis communications plan, which a continuity test exercises rather than produces. | I28: n/a | J28: Results resolve the capability states the row above leaves as not yet tested, which is the join between the two. Recording a failed or partial test matters more than recording a passed one, and the capture form has to make that easy rather than awkward.
A29: The disruption
A30: Responding to a disruption | B30: Declare, invoke the action plan, communicate, restore, judge against the operative tolerance, notify, close. The only process fired by the outside world. | C30: Incident and issue store, Capability assessment records (a real disruption is evidence) | D30: Input, from the outside world: a person declares a disruption, or a monitoring signal detects one. The only process in either area not initiated by the Company or fired by cron. | E30: 2: disruption declaration; and the incident capture that already exists for the underlying event. | F30: 3: BCP invocation and execution; crisis communications despatch; tolerance breach evaluation against the operative tolerance, returning an explicit indeterminate result where a tolerance defers to capability. | G30: 1: a live disruption view. Which operation, elapsed against tolerance, which action plan steps are done, and what has been communicated. Distinct from the standing dashboard, which asks whether the Company could cope rather than whether it is coping. | H30: The BCP action plan for the affected operation, and the crisis communications plan. Both have to exist beforehand; neither can be written during. | I30: Reportable situation or prudential notification where a regime engages, plus any customer or adviser communication the plan carries. | J30: The row where the deep dive found the most missing. Nothing declares a disruption, nothing invokes an action plan, and nothing despatches the communications plan. The plans are being written and nothing runs them. Because the trigger is external there is no scheduled moment when someone remembers, which is why the declaration form matters far more than its size suggests.
A31: The provider
A32: Onboarding a material service provider | B32: Materiality assessment, contract, and an exit plan before reliance begins rather than after. | C32: Material service providers | D32: Input: a new or changed provider arrangement is notified. | E32: 1: provider notification, capturing the arrangement, the service relied on and the contract. | F32: 1, with a materiality gate: AI drafts a materiality view against the CPS 230 criteria, the CRO determines, and the monitoring cadence and exit-plan obligation follow from that determination. | G32: 1: material service providers, by materiality, monitoring status, contract end and exit plan test status. | H32: The contract, and the exit plan, which CPS 230 requires before reliance begins rather than after. | I32: The provider joins the annual submission at the last row. | J32: Nothing captures a provider today, which is why only AWS is recorded while the operating model depends on AI providers, reinsurers and payment providers. That is the most visible single gap in this area at the licence application.
A33: Monitoring a provider | B33: A cycle at the cadence materiality set, raising any shortfall into gap closure. | C33: Provider monitoring records | D33: Cron, per provider, at the cadence its materiality determination set. Also input, on a provider-reported incident or a service level failure. | E33: 1: monitoring outcome capture, with evidence. | F33: 1: the monitoring cycle, raising anything short into the gap closure process above. | G33: 1: a slice of the provider dashboard, showing monitoring status and anything overdue. | H33: n/a | I33: n/a: rolls into the annual submission at the last row. | J33: The monitoring cycle existed in the backlog and the store for its outcomes did not, so the provider dashboard had nothing to read. That store is new.
A34: Exiting a provider | B34: Planned or forced, where the exit plan is executed rather than tested. | C34: Material service providers, Test execution store | D34: Input: a decision to exit, or a provider failure forcing one. Also cron, on an approaching contract end date. | E34: 1: exit initiation, recording whether the exit is planned or forced. | F34: 1: execute the exit plan, transition or terminate the service, confirm data return or destruction, and close the arrangement on the register. | G34: 1: a slice of the provider dashboard, showing exits in progress against plan. | H34: The exit plan, executed rather than tested. | I34: Notification to APRA on a change to a material arrangement [confirm what CPS 230 requires and when]. | J34: Distinct from the exit plan test, where the same plan is exercised. A forced exit is a disruption as well as an exit, so the disruption process runs alongside this one, and the two must not fight over the same incident record.
A35: Reporting
A36: Regular reporting | B36: The annual Board paper and the annual provider submission, reconciling two stores that have to agree. | C36: Lodgement and submission records | D36: Cron: annual for the Board paper and the APRA submission, and per meeting for the Board and committee cycle. | E36: 1: management commentary, and the materiality-trigger judgement the paper turns on. | F36: 2: the annual Board paper, reconciling the register against the capability assessment and applying the materiality trigger; and the annual material service provider submission. | G36: 1: reporting readiness and what is overdue. | H36: The annual operational resilience Board paper. | I36: Annual material service provider register submission to APRA. | J36: The paper reconciles two stores that have to agree, so it is the one place a divergence between the critical operations register and the capability assessment becomes visible. That is an argument for the assessment being child records of the register rather than a store beside it.
A38: Incident, breach and issue | B38: The four views, breach, operational incident and near-miss, security, and data quality, are configurations of this one lifecycle rather than four processes. They differ in owner, regime and clock, not in shape.
A39: The issue
A40: Reporting or detecting an issue | B40: Four capture paths into one store: a person, a system rule, another governance process, or off-platform while the platform itself is down. | C40: Incident and issue store | D40: Input, four ways: a person uses the four-button entry page; a system rule fires, such as a data quality failure or an overdue clock; another governance process raises one, such as controls assurance, an audit finding, a complaint or a disruption; or an off-platform record is submitted once availability returns. | E40: 2: the four-button entry page; and the off-platform fallback for use while the platform is unavailable. | F40: 2: capture and typing into the store; and reconciliation of off-platform records once availability is restored. | G40: 1: a slice of the incident and breach measures, showing what has been raised and through which path. | H40: n/a: CPL-3 is the policy and sits in the suite. | I40: n/a: nothing files on capture. Notification is a later row. | J40: The store is built. The form exists and any staff member may use it, but it is reached from inside a risk case-management page rather than being a front door, which matters more here than the effort suggests: twenty people, no compliance department, and no other route by which a problem reaches the Risk function. The off-platform path is dated January 2027.
A41: Triaging and classifying it | B41: Where the statutory clocks start, held separately from the state change so a later reclassification cannot rewrite when the clock began. | C41: Incident and issue store (the assessed field set) | D41: Input: a new record arrives in the store. Also input, where new information changes an earlier classification. | E41: n/a: classification is a task on the record already captured, not a second form. | F41: 2: classification into one of the four views with the three-state regime determination; and the significance assessment that decides whether a breach is reportable. | G41: 1: clocks approaching and overdue, by regime. | H41: n/a | I41: n/a: the determination is what sends a matter to the notification row, rather than filing itself. | J41: The store's three-state regime field and its split light and assessed field sets are built, and so is the clock engine. The determination workflow over them is not. Two notification timeframes remain unconfirmed; they are held as data, so confirming them is a setting rather than a build, and they can be left unconfirmed without blocking anything.
A42: Investigating it | B42: Root cause, whether the matter is systemic, and the links that unlock the ninety-day extended timeframe. | C42: Incident and issue store | D42: Input: a matter classified as requiring investigation. Also cron, at sixty days, which is itself a reportable situation. | E42: n/a: findings and evidence are recorded against the matter as workflow tasks. | F42: 3: investigation and root cause; similar-circumstances linking, where AI proposes and a person confirms; and the sixty-day trigger. | G42: 1: ageing investigations, and anything past sixty days. | H42: n/a | I42: 1: the sixty-day overrun is itself a reportable situation and files through the row below. | J42: Built, including the linking step, which was created by reusing the AI-draft and human-confirm shape unchanged. That is the clearest evidence in the whole register that a shape built once becomes configuration rather than a build.
A43: Notifying a regulator | B43: One workflow configured per regime, sharing its shape with the FAR, CPS 520 and provider notifications. | C43: Regulator submission record | D43: Input: a determination at triage that a regime engages. Escalates as the computed due date approaches. | E43: 1: notification content and the approval decision. | F43: 1, configured per regime: ASIC reportable situations, APRA prudential notification, and the OAIC notifiable data breach path [assumed required by CUS-1 and CUS-6; confirm]. Draft, approve, lodge, record. | G43: 1: notifications due, lodged and overdue by regime. | H43: The notification itself, versioned, and the evidence of what was lodged. | I43: The notification to each regulator, with lodgement date, recipient and reference. | J43: The clock engine, the regime rules and the submission record are all built. The draft, approve and lodge sequence over them is not. Because the shape is shared with the FAR s32, CPS 520 and material service provider notifications, this is one workflow with five configurations rather than five workflows.
A44: Remediating and closing | B44: The fifth instance of the closure shape, after audit findings, privacy findings, controls assurance remediation and resilience gaps. | C44: Incident and issue store (closure state and evidence) | D44: Input: an investigation concluded, or a control fix or customer remedy determined. | E44: 1: closure evidence and the remediation record. | F44: 2: control fix and closure with an acceptance gate and a reopen path; and customer remediation where customers were affected, which carries a later gate. | G44: 1: open matters by age, and anything reopened. | H44: n/a | I44: n/a | J44: Customer remediation sits after go-live on the assumption that at launch volumes a remediation can be run by hand. That assumption should be revisited as in-force volume grows, because the point at which it fails is not obvious in advance.
A45: Reporting
A46: Regular reporting | B46: Individual notifications exist. The aggregate view the Board reads does not. | C46: Lodgement and submission records | D46: Cron, per the Board and Risk Committee meeting cycle. | E46: 1: management commentary on themes, and anything the numbers do not show. | F46: 1: assemble volumes, ageing, overdue clocks, what was notified and the themes the confirmed links expose, then route to the Risk Committee. | G46: 1: the incident and breach measures the report draws on. | H46: The periodic incident and breach report. | I46: To the Board and Risk Committee, and into the annual reporting cycle. | J46: This was recorded as a gap in the area matrix, and the process view shows why it was understated: the four views were counted as this area's dashboard, but they are filtered lists over the store rather than measures against a threshold. They answer what is open, not whether the Company is keeping up.
A48: Compliance and obligations | B48: Two things to carry out of this area. Rows two to five all depend on the obligations population workplan, which is compliance work rather than a build: tooling over a register holding test data buys nothing. And risk identification, the AI capability that reads a document and identifies the risks it raises, is filed in this area only because nothing better exists. The risk register, risk identification and risk rating are not among the seventy-four artefacts at all, while appetite and key risk indicators sit under Delegations and Board. That looks like a missing area rather than a misfiled row.
A49: The obligation
A50: Identifying a source instrument | B50: Deciding what actually applies to the Company. The top of the pipeline, and what every row below inherits from. | C50: Sources and instruments in the obligations pipeline; the nine compliance domains and their first-line owners as reference data alongside them | D50: Input: a new instrument is identified, or a regulator amends one. Also cron, an annual sweep of the regulatory environment against the product roadmap. | E50: 1: source instrument capture, carrying the paragraphs, the domain and the source. Also the route by which someone who spots a missing obligation gets it in, since an obligation is drafted from an instrument rather than proposed on its own. | F50: 1: scoping and applicability. AI drafts the reasoning, the CRO determines in or out of scope with the reason recorded, and what was excluded is evidenced as deliberately as what was included. | G50: 1: a slice of the compliance measures, showing instruments in scope by domain and anything scoped but not yet drafted from. | H50: n/a: CPL-2 is the framework and sits in the suite. | I50: n/a | J50: The pipeline holds sources, instruments and paragraphs and is built. The capture form and the scoping determination over it are not, so the instruments currently in it were loaded rather than scoped through a governed path. First-line domain ownership is folded in here as reference data because a domain is scoped at the same time as the instruments that fall in it.
A51: Creating obligations from an instrument | B51: AI drafts from the paragraphs, the CRO validates, an owner and a control attach. Built and working, and holding test data. | C51: Obligations in the pipeline, with owner as a real reference to a function | D51: Input: an instrument scoped in, or a paragraph added to one already in scope. | E51: n/a: drafting is AI, validation is the CRO's task on the draft. There is nothing for a person to fill in. | F51: 1: AI drafts the obligation, the CRO validates, and owner, control and history are recorded. | G51: 1: a slice of the compliance measures, showing obligation coverage by domain and obligations without a control. | H51: n/a | I51: n/a | J51: The tooling is built and the owner reference was hardened from a name-matched string. What has not been done is the work: reading each instrument and drafting the obligations it creates. Some of what sits in the register today is test data to be replaced. That is a compliance workplan rather than a build, and it is the dependency under this row and the next three, because tooling over an unpopulated register buys nothing.
A52: Refreshing obligations when an instrument changes | B52: The regulator amends something, and the affected obligations have to be found, redrafted and revalidated. | C52: Obligations in the pipeline, with version history and the reason | D52: Input: a change detected in a scoped instrument. Also cron, a periodic re-check that scoped instruments are still current. | E52: n/a: the change arrives against the instrument, and revalidation is the CRO's task. | F52: 1: detect the changed instrument, AI drafts the affected obligations, the CRO validates, and owners and controls are updated rather than duplicated. | G52: 1: a slice of the compliance measures, showing obligations pending revalidation. | H52: n/a | I52: n/a | J52: Sequenced behind the population workplan. Refreshing a population that was never properly created has no value, so this row is not the constraint even though it is unbuilt.
A53: The control
A54: Defining or changing a control | B54: The row nothing covers. Three other rows point at controls and nothing in the register defines what a control is. | C54: Control register: description, owner, preventive or detective, operating frequency, evidence method | D54: Input: a new control is designed, or an existing one is amended, or an obligation arrives with nothing to discharge it. | E54: 1: control definition capture, with the obligations it discharges. | F54: 1: the first-line owner defines or amends, AI proposes the obligations it discharges, the CRO confirms the linkage and the classification, and the control is versioned. Where a control changes, obligations that relied on the prior version are re-linked rather than silently inheriting. | G54: 1: a slice of the compliance measures, showing controls by owner and any without a linked obligation. | H54: n/a | I54: n/a | J54: Flagged as an assumption rather than asserted: controls may already be first-class objects inside the obligations pipeline, in which case this is a description gap rather than a build. Engineering should settle it before anything is built, because three rows depend on the answer.
A55: Linking a control to an obligation | B55: AI proposes, the CRO confirms. The one missing step in an otherwise built graph. | C55: Control and obligation linkage | D55: Input: a new obligation, or a new or changed control. | E55: n/a: confirmation is a task on the proposed linkage. | F55: 1: AI proposes the linkage with its reasoning, the CRO confirms or rejects, and the decision is recorded. | G55: 1: a slice of the compliance measures, showing obligations with no control and controls with no obligation. | H55: n/a | I55: n/a | J55: The graph, its edges and the control-failure link are all built, and the owner is a real reference. What is absent is the AI-propose step, which is a plain reuse of the shape already running the obligations pipeline and the issue linking. One of the cheapest items in the register.
A56: Testing a control | B56: The assessment cycle. The store exists and nothing prompts the cycle, so testing can be recorded but only when someone remembers. | C56: Controls assurance: testing plan, execution, evidence, remediation, and the audit log of what was tested by whom | D56: Cron, per the control's testing cadence, fanned out one assessment per control. Also input, where a change or an incident calls a test early. | E56: 1: test execution and evidence capture. | F56: 1: the assessment cycle, with remediation raising into the closure shape. | G56: 1: a slice of the compliance measures, showing controls tested against plan and anything overdue. | H56: n/a | I56: n/a | J56: This is why the item sits in Group 2 rather than Group 1 in the inventory: the store is built, and what is outstanding is the cycle that drives it. Configuring cadence, assessor and overdue escalation against the assessment primitives is what turns a place to record testing into testing that reliably happens.
A57: Recording a control failure | B57: Where the arrangements-inadequate limb becomes answerable from data rather than memory. | C57: Control and obligation linkage with failure history; the incident store where a regime engages | D57: Input, three ways: a test fails, an incident reveals a control did not operate, or someone notices and reports it. | E57: 1: control failure recording, against the control and the obligations it was discharging. | F57: 2: record the failure and increment the count; and assess whether the failure makes the arrangements inadequate and whether it is a reportable situation, which sends it into the incident process. | G57: 1: failure counts by control and by obligation. The inventory records that nothing aggregates failures into a number a significance test could use, and this is that number. | H57: n/a | I57: Where the failure is a reportable situation it files through the incident area's notification row. | J57: Failures do not only come from testing, which is why this is a row rather than a step inside the one above. The count is the point: a single control failure is a finding, and the same control failing four times is an inadequate arrangement, and only the aggregate distinguishes them.
A58: Reporting
A59: Regular reporting | B59: CPL-2 assumes this reporting happens. Nothing generates it. | C59: Lodgement and submission records | D59: Cron, per the Risk Committee meeting cycle. | E59: 1: management commentary on themes and anything the numbers do not show. | F59: 1: assemble obligation coverage, testing completed against plan, failures and their significance, and open remediation, then route to the Risk Committee. | G59: 1: the compliance measures the report draws on. | H59: The periodic compliance report. | I59: To the Risk Committee, and into the annual Board reporting cycle. | J59: One of the three matrix gaps this area carried. The other two, the entry form and the dashboard, are closed by the rows above.
A61: Information security | B61: The least-built area so far: nothing exists, and every item sits on the February to March 2027 timeline. Two things are flagged rather than asserted, both recorded in the register so the decision is visible: key and secret custody, which no artefact covers and which may be deliberate; and whether CPS 234 requires an annual attestation at this scale.
A62: The information asset
A63: Classifying an information asset | B63: The analogue of role creation and of defining a critical operation: classify the thing, and the controls follow from the classification. | C63: Information asset classification inventory, including the operator fields moved here from People, and key and secret custody | D63: Input: an asset is created or materially changed. Also cron, a periodic reclassification review, since an asset moving tier changes the controls that must apply to it. | E63: 1: asset classification capture, carrying owner, criticality, sensitivity tier and named operators. | F63: 1: the owner classifies, the system derives the controls for that tier and records them against the asset, the COO confirms, and a reclassification review is scheduled. | G63: 1: a slice of the security measures, showing assets by tier and anything unclassified. | H63: n/a: OPS-5 is the framework and sits in the suite. | I63: n/a | J63: Nothing in this area is built; the inventory is dated February 2027. Key and secret custody is recorded here as a flagged assumption: OPS-5 sets out encryption and nothing in the seventy-four artefacts covers key custody, rotation or recovery. It may be deliberate, on the basis that it is infrastructure rather than a governance artefact. It is in the register so the decision is visible rather than absent.
A64: Granting, changing or revoking access | B64: One lifecycle with three transitions, and the subject may be a person, a system or an AI agent. | C64: Access record: which subject has access to which asset, at what level | D64: Input, three ways: an appointment grants, a role change alters, a departure or a withdrawal of need revokes. Also input, a specific request outside those events. | E64: 1: access request and change capture, against a named asset and level. | F64: 1 with three transitions: grant, change and revoke. The asset owner approves against the sensitivity tier, and the record extends to systems and AI agents rather than only people. | G64: 1: a slice of the security measures, showing access by subject type and anything granted without an approval record. | H64: n/a | I64: n/a | J64: This row is coupled to the People rows and mostly fired by them rather than initiated here. If appointment and departure do not set and revoke access, the access record is wrong from the first day it exists, and a stale access record is worse than none because it is evidence of a control that is not operating. That coupling is the single most important thing in this area.
A65: Recertifying access | B65: Periodic confirmation that the access shown is access still needed. | C65: Access record | D65: Cron, fanned out per asset owner. [ASSUMPTION: six-monthly. OPS-5 §3 requires the record but states no recertification cadence.] | E65: n/a: confirmation is the assessor's task against the list already held. | F65: 1: the assessment shape, where the assessor confirms each subject still needs the access shown and anything unconfirmed is revoked rather than left. | G65: 1: a slice of the security measures, showing recertifications completed and overdue. | H65: n/a | I65: n/a | J65: The default matters here: access unconfirmed at the end of a cycle should be revoked rather than carried, because the alternative is that a recertification which nobody completes leaves the record exactly as wrong as it was, while appearing to have been checked.
A66: Testing
A67: Running a security test | B67: One row, three configurations, and the fourth and fifth uses of the shared test execution store. | C67: Test execution store; the security control testing programme's plan, scope and cadence | D67: Cron, per the testing plan. Also input, where a change or an incident calls a test early. | E67: 1: test result capture, shared with the resilience testing programme. | F67: 3 configurations of one shape: control effectiveness testing, penetration testing with an external provider performing the test task and the COO accepting the result, and the response plan exercise across the three scenarios. | G67: 1: a slice of the security measures, showing testing completed against plan and open findings. | H67: The security incident response plans, which the exercise configuration tests rather than produces. | I67: n/a | J67: The plan, scope, cadence and provider are all flagged as not yet built, which means the programme is currently a date rather than a plan. Findings raise into the closure shape, which is now its sixth instance.
A68: The incident
A69: Responding to a security incident | B69: The plans are written and tested annually. Nothing invokes one. | C69: Incident and issue store (the security view); the response plan steps as executed | D69: Input: a security event detected or reported, arriving through the incident area's capture paths. | E69: n/a: capture is the incident area's entry page rather than a second form here. | F69: 1: select the plan for the scenario, contain, execute the plan steps, and record each against the incident. The same shape as BCP invocation in operational resilience. | G69: 1: a slice of the security measures, showing incidents and their containment. | H69: The response plan for the scenario: provider compromise, unauthorised access, or an AI system operating outside its function. | I69: CPS 234 notification of a material incident, and separately of a material control weakness, as configurations of the shared notification workflow. | J69: Filed here rather than in the incident area because the plan invocation and the CPS 234 notification are specific to security, while the record itself lives in the incident store's security view. The same split as disruption response: one area owns the response, another owns the record. The third scenario, an AI system operating outside its function, has no external precedent to lean on and is specific to this operating model.
A70: Reporting
A71: Regular reporting | B71: Both the dashboard and the report were gaps in the area matrix. CPS 234 makes this the Board's business. | C71: Lodgement and submission records | D71: Cron, per the Board and committee cycle for the report, and annually for the attestation. | E71: 1: management commentary on themes and anything the numbers do not show. | F71: 1: assemble classification coverage, access anomalies, testing and findings, incidents and containment, and open remediation, then route to the Board. | G71: 1: the security measures the report draws on. | H71: The periodic security report. | I71: To the Board; and a CPS 234 annual attestation [assumption, flagged: whether an attestation or return applies at this scale has been an open question since the area matrix was built and is still unconfirmed]. | J71: The attestation is written in flagged rather than left as a silent gap, so that confirming or striking it is a decision someone takes rather than an omission nobody notices.
A73: Data governance | B73: Questions in the Notes column are flagged for the design phase rather than answered here. The job at this stage is the breadth of the work, and these are better settled when each line item is designed. They are collected on the Questions sheet.
A74: The data item
A75: Defining or changing a data item | B75: The dictionary is what everything else in this area measures against, including what 'mandatory' means. | C75: Data dictionary, lineage records, and the seven data domains with their accountable executives | D75: Input: a schema change, a new field, or a new report or decision that relies on an existing item. Also cron, a periodic review of definitions against what the systems actually hold. | E75: 1: data item definition capture, carrying the definition, permitted values, mandatory flag and domain. | F75: 1: the domain owner defines or amends, lineage is recorded from capture through to the reports and decisions relying on the item, the COO confirms the mandatory flag, and the item is versioned. | G75: 1: a slice of the data quality measures, showing items defined against items in use and anything undefined. | H75: n/a: OPS-6 is the framework and sits in the suite. The data structure diagrams are satisfied by the logical architecture diagram at OPS-1 §6. | I75: n/a | J75: QUESTION for the design phase: whether lineage is derived from the platform automatically or maintained by hand. If derived, it is a system task inside this workflow. If maintained, it is a second form and an ongoing burden that will rot. OPS-6 §2 requires the tracing and does not say how. Also worth noting the seven data domains here are a different cut from the nine compliance domains, and nobody should try to reconcile them.
A76: Data quality
A77: Defining a data quality rule | B77: The rules are the mechanism behind the claim that month-end reconciliation disappears. | C77: Data quality rule register: domain, item, completeness or consistency, threshold, window, severity | D77: Input: a new item or domain, a new report that depends on an item, or a recurring issue that shows a rule is missing. | E77: 1: rule definition capture, with the threshold and window. | F77: 1: the domain owner proposes, AI checks the rule against the dictionary for items it cannot test, the COO approves, and the rule is scheduled. | G77: 1: a slice of the data quality measures, showing rules per domain and domains with no rule. | H77: n/a | I77: n/a | J77: A rule that references an item with no definition is the common failure, which is why the dictionary gates this rather than the reverse. QUESTION for the design phase: whether the rules engine already holds rules as first-class configurable objects, in which case the rule register is a description gap rather than a build. This is the same question as the control register in compliance and should be answered once for both.
A78: Running the rules and raising issues | B78: Deterministic, scheduled, and the only row in this area that needs no person. | C78: Windowed issue records generated per rule | D78: Cron, per rule at its own window. | E78: n/a: the engine raises issues. A person who notices a data problem uses the four-button entry page in the incident area rather than a form here. | F78: 1: execute the rules, generate windowed issue records, and pass anything above threshold to resolution. | G78: 1: rates per domain against target, and the volume and age of outstanding issues. | H78: n/a | I78: n/a | J78: Scoped at go-live to the rules behind the APRA return and the ledger rather than all seven domains. That protects the regulatory numbers and quietly accepts manual effort elsewhere for a period, which is a cost worth naming rather than discovering.
A79: Resolving a data quality issue | B79: Correction at source where possible, cleansing where it is not, with the reason recorded either way. | C79: Issue records with resolution and evidence | D79: Input: an issue raised above threshold by the rules, or a data problem reported by a person through the incident entry page. | E79: 1: resolution evidence and the reason, since correcting at source and cleansing after the fact are different answers and the difference matters later. | F79: 1: the closure shape, with an acceptance gate and a reopen path. The seventh instance of this shape. | G79: 1: a slice of the data quality measures, showing outstanding issues by age and by domain. | H79: n/a | I79: n/a | J79: The distinction the row turns on: a cleansed value is right now and wrong again next time, while a correction at source stops the issue recurring. If the resolution record does not force that choice to be stated, the metric improves while the underlying problem persists.
A80: End-user computing
A81: Registering an end-user computing tool | B81: A spreadsheet or extract starts feeding a decision or a return, and has to be inventoried. | C81: End-user computing inventory: purpose, owner, version control, methodology, reconciliation | D81: Input: a tool outside the single data source starts feeding a decision or a return. | E81: 1: registration, with the purpose and the reconciliation method. | F81: 1: the owner registers it, the COO confirms it is needed rather than a symptom of a missing system capability, and a reconciliation cadence is set. | G81: 1: a slice of the data quality measures, showing registered tools by owner. | H81: n/a | I81: n/a | J81: OPS-6 §2 makes a spreadsheet the expensive option rather than the cheap one, because anything outside the single data source picks up inventory, version control and reconciliation obligations. The confirmation step exists so that registering a tool is a moment to ask whether the platform should do the job instead.
A82: Reconciling an end-user computing tool | B82: The periodic confirmation that makes the inventory a control rather than a list. | C82: End-user computing inventory | D82: Cron, per tool. [ASSUMPTION: annual.] | E82: 1: reconciliation evidence. | F82: 1: the assessment shape, confirming version control, methodology and reconciliation per tool. | G82: 1: a slice of the data quality measures, showing anything unreconciled or overdue. | H82: n/a | I82: n/a | J82: Split out by the Map, which showed the original row was doing two lifecycle stages at once: registering is an event and reconciling is a cycle, and merging them hid the fact that only one of the two was described.
A83: De-identified data
A84: Confirming a de-identification method before use | B84: The confirmation is the control, and it binds on the first use rather than on a date. | C84: De-identification method register: which method applies to which use, and the confirmation | D84: Input: a new analytics or model-development use of de-identified data is proposed. | E84: 1: use request, naming the use and the method proposed. | F84: 1: the requester names the use, AI drafts whether the method is fit for it, and the CRO confirms before the data is used. | G84: n/a: a register of confirmations does not need a measure at this volume. | H84: n/a | I84: n/a | J84: QUESTION for the design phase: the register is gated at +12 months, but 'confirmed fit for that use before use' binds on the first such use. If any analytics or model-development use of customer data happens earlier, this is needed earlier, and the gate should follow the first use rather than the register's date.
A85: Reporting
A86: Regular reporting | B86: Reaches the Board through the Board pack rather than through a return of its own. | C86: Lodgement and submission records | D86: Cron, per the Board and committee cycle. | E86: 1: management commentary on themes and on anything the rates do not show. | F86: 1: assemble rates per domain against target, outstanding issues by age, and cleansing progress, then route into the Board pack. | G86: 1: the data quality measures the report draws on. | H86: The data quality report. | I86: n/a: nothing files with a regulator. The numbers reach APRA through the returns the data supports rather than as a submission about data quality. | J86: The only area so far whose reporting produces a document and no return, which is why the area matrix records its Report column as deliberately blank rather than as a gap.
A88: Conflicts and related party | B88: The area whose principal entries already exist and are structural rather than hypothetical, which makes the initial population the real work and the tooling secondary. It is also the area that exposed a missing attribute rather than a missing process: nothing records which directors are unaffiliated, and two processes here need to know.
A89: The conflict
A90: Disclosing a conflict and deciding the response | B90: Logged within five business days whether or not a response is decided, which makes logging and deciding two steps with two clocks. | C90: Conflicts register | D90: Input: a person discloses an interest. Also input, on a trigger event: an appointment, a new arrangement, or a change in a related party's business. | E90: 1: the disclosure form, which has to accept a record with no response yet. | F90: 1 with two timed steps and a routing rule: log within five business days, then the CRO decides the response, or the Chair where a director is involved. Avoid, control or disclose, with the next review date set from the response. | G90: 1: conflicts logged with no response decided, and how long they have been waiting against the five-day rule. | H90: n/a: GOV-9 is the policy and sits in the suite. | I90: n/a: nothing files on disclosure. The Board sees it through reporting. | J90: The field-set split the five-day rule needs is exactly what the incident store already does with its light and assessed field sets, so this is likely a reuse rather than a design. Routing depends on who is involved, which needs director affiliation held as data rather than judged each time.
A91: Reviewing a conflict | B91: A conflict whose response is never revisited is a control that stopped operating without anyone deciding to stop it. | C91: Conflicts register | D91: Cron, from each conflict's next review date. Also input, where the underlying circumstances change. | E91: n/a: confirmation is the reviewer's task on the record already held. | F91: 1: the review shape. AI drafts whether the response is still adequate, the CRO or the Chair confirms, amends, or records the conflict as ceased. | G91: 1: a slice of the conflicts measures, showing reviews due and overdue. | H91: n/a | I91: n/a | J91: Cessation is an outcome of this review rather than a process of its own, which is why the Map shows no Exit stage for a conflict.
A92: The related-party arrangement
A93: Approving a related-party arrangement | B93: C9 reviews arrangements annually. Nothing approved them in the first place. | C93: Related-party arrangement register, with the benchmark and the approval | D93: Input: a standing arrangement with a related party is proposed or identified. | E93: 1: arrangement capture, with the parties, the service, the terms and the benchmark relied on. | F93: 1: the Company Secretary records it, AI drafts whether it is a related-party arrangement and what benchmark applies, the system identifies the unaffiliated directors from the role record, and those directors approve the terms as arm's length with the benchmark attached. | G93: 1: a slice of the conflicts measures, showing arrangements with their approval and benchmark status. | H93: The benchmark evidence, held against the arrangement. | I93: n/a: approval is internal. It reaches APRA through the application and then through reporting. | J93: The step that needs something nobody holds: the requirement names unaffiliated directors and nothing records which directors are unaffiliated. That is an attribute on the role record, and it is now a register item in the People area rather than here.
A94: Reviewing a related-party arrangement | B94: Annual, with the benchmark refreshed rather than assumed to still hold. | C94: Related-party arrangement register: the annual review outcome | D94: Cron, annual, fanned out per standing arrangement. | E94: 1: the refreshed benchmark and the review outcome. | F94: 1: the assessment shape, with the arm's-length benchmark as evidence and the unaffiliated directors as the assessors. | G94: 1: a slice of the conflicts measures, showing reviews completed and overdue. | H94: The refreshed benchmark. | I94: Into the related-party and conflicts report the Board and the unaffiliated directors read. | J94: A benchmark that is not refreshed becomes an assertion about a market that has moved. Whether refreshing it needs an external source, and what that costs, is a design-phase question.
A95: Ending or renegotiating an arrangement | B95: Live rather than theoretical: the Retender arrangements are the ones most likely to change. | C95: Related-party arrangement register | D95: Input: an arrangement ends, or its terms change. | E95: 1: the end or the change, and what replaced it. | F95: 1: where terms change, back through approval rather than amended in place, since new terms need a new arm's-length finding. Where it ends, the entry is closed with what replaced it recorded. | G95: 1: a slice of the conflicts measures. | H95: n/a | I95: n/a | J95: Amending an approved arrangement in place is the failure mode this row exists to prevent: the approval attaches to the terms, so changed terms need a fresh one.
A96: Reporting
A97: Regular reporting | B97: Both of this area's matrix gaps sit here, and the audience is unusual: the unaffiliated directors as well as the Board. | C97: Lodgement and submission records | D97: Cron, per the Board and committee cycle, and annually for the arrangement reviews. | E97: 1: management commentary, and anything the register does not show. | F97: 1: assemble open conflicts and their responses, arrangements with their benchmarks and review outcomes, and training completion, then route to the Board and to the unaffiliated directors. | G97: 1: the conflicts and related party measures. | H97: The related-party and conflicts report. | I97: To the Board and the unaffiliated directors. | J97: This is the most scrutinised area in the application, and the register is empty. The initial population of the known structural conflicts is the real work here, not the tooling: two Retender co-founders as executives, brokerage on business the Company helps place, and a cornerstone investor director. If the register is empty at lodgement the tooling does not help, which is the same shape as the obligations population.
A99: Risk management | B99: The area that did not exist until the OPS-1 §7 sweep. The risk register is described in §7 as a system the Company has and was absent from the seventy-four artefacts, because the inventory found what governance documents assert rather than what the business runs.
A100: The risk
A101: Identifying a risk | B101: Raised by a person, or drafted by AI from a document, with duplicates flagged rather than created. | C101: Risk register | D101: Input: a person raises one, or a business document, proposal, plan or policy is read by the AI capability. Also input, from an incident, an audit finding or a control failure. | E101: 1: risk capture, with the cause and the exposure it creates. | F101: 1: AI reads the document and identifies the risks it raises, flags candidates already on the register, and proposes an owner; a person adds, discards, merges or reassigns before anything is recorded. | G101: 1: a slice of the risk measures, showing what was raised and from where. | H101: n/a: RSK-1 is the strategy and sits in the suite. | I101: n/a | J101: Built, and the only thing in this area that is. The register it writes to was absent from the inventory entirely, because no governance document asserts the risk register as an artefact to be built even though OPS-1 §7 describes it as a system the Company has.
A102: Assessing and rating a risk | B102: Rating without recording the basis is the failure mode: the number survives and the reasoning does not. | C102: Risk register: rating, basis, appetite category, review date | D102: Input: a risk recorded. Also input, where an incident or a control failure changes the exposure. | E102: n/a: the rating is a task on the risk already captured. | F102: 1: the owner or AI proposes a rating, the system checks which appetite category it falls in, the CRO confirms, and the rating is recorded with its basis. | G102: 1: risks by rating and by appetite category. | H102: n/a | I102: n/a | J102: The appetite check is the join to RSK-2: seventeen appetite categories exist and nothing currently maps a rated risk to the category it consumes.
A103: Reviewing a risk | B103: Reassess, confirm the treatments operate, or close with a reason. | C103: Risk register | D103: Cron, from each risk's review date. Also input, on a material change in the exposure. | E103: n/a: confirmation is the reviewer's task. | F103: 1: the review shape. Reassess the rating, confirm treatments are operating, or close the risk with a reason recorded. | G103: 1: a slice of the risk measures, showing reviews due and overdue. | H103: n/a | I103: n/a | J103: Closing a risk with a reason is what stops the register growing monotonically, which is the usual fate of a risk register nobody is allowed to close anything on.
A104: Treating a risk | B104: Closure shape again, its eighth instance. | C104: Risk treatments and actions | D104: Input: a treatment agreed during assessment or review. | E104: 1: treatment progress and closure evidence. | F104: 1: owner, target date, progress, evidence, acceptance or reopen, with overdue escalation. | G104: 1: a slice of the risk measures, showing treatments by age and anything overdue. | H104: n/a | I104: n/a | J104: Identical in shape to audit findings, resilience gaps, data quality issues, incident remediation, controls assurance remediation and privacy findings. Eight instances of one workflow.
A105: Reporting
A106: Regular reporting | B106: The register by rating, movements, treatments, and exposure against each appetite statement. | C106: Lodgement and submission records | D106: Cron, per the Risk Committee meeting cycle. | E106: 1: management commentary on movements and on anything the ratings do not show. | F106: 1: assemble the register by rating, movements since last cycle, treatment status and appetite exposure, then route to the Risk Committee. | G106: 1: the risk measures the report draws on. | H106: The periodic risk report. | I106: To the Risk Committee and the Board. | J106: RSK-1 and RSK-2 both assume this reporting happens. The appetite exposure half cannot be produced until a rated risk maps to an appetite category, which is the join named two rows above.
A108: Delegations and Board | B108: The area every other area's reporting row points into. Its own build is small: a delegation register held as data, and a roll-up view over decisions the engine already records.
A109: Delegations
...
